jsonml/__init__.py
jsonml/exporter.py
jsonml/parser.py
jsonml-0.0.3.dist-info/WHEEL
jsonml-0.0.3.dist-info/METADATA
jsonml-0.0.3.dist-info/RECORD
